Cue/__init__.py
Cue/clip.py
Cue/controller.py
Cue/exceptions.py
cue_audio-1.0.0.dist-info/licenses/LICENSE
cue_audio-1.0.0.dist-info/METADATA
cue_audio-1.0.0.dist-info/WHEEL
cue_audio-1.0.0.dist-info/top_level.txt
cue_audio-1.0.0.dist-info/RECORD
