Metadata-Version: 2.4
Name: cue-audio
Version: 1.0.0
Summary: Simple, elegant spatial audio orchestration for immersive experiences
Home-page: https://github.com/alexwales/cue-audio
Author: Alex Wales
Author-email: alexwaiteuk@gmail.com
Project-URL: Bug Reports, https://github.com/alexwales/cue-audio/issues
Project-URL: Source, https://github.com/alexwales/cue-audio/
Project-URL: Documentation, https://github.com/alexwales/cue-audio#readme
Keywords: audio spatial surround mqtt immersive sound automation
Classifier: Development Status :: 4 - Beta
Classifier: Intended Audience :: Developers
Classifier: License :: OSI Approved :: MIT License
Classifier: Operating System :: OS Independent
Classifier: Programming Language :: Python :: 3
Classifier: Programming Language :: Python :: 3.8
Classifier: Programming Language :: Python :: 3.9
Classifier: Programming Language :: Python :: 3.10
Classifier: Programming Language :: Python :: 3.11
Classifier: Programming Language :: Python :: 3.12
Classifier: Topic :: Multimedia :: Sound/Audio
Classifier: Topic :: System :: Hardware
Classifier: Topic :: Home Automation
Requires-Python: >=3.8
License-File: LICENSE
Requires-Dist: pyaudio>=0.2.11
Requires-Dist: paho-mqtt>=1.6.0
Requires-Dist: numpy>=1.21.0
Dynamic: author
Dynamic: author-email
Dynamic: classifier
Dynamic: description
Dynamic: description-content-type
Dynamic: home-page
Dynamic: keywords
Dynamic: license-file
Dynamic: project-url
Dynamic: requires-dist
Dynamic: requires-python
Dynamic: summary
